xqa
