Metadata-Version: 2.1
Name: pyXqa
Version: 0.0.2
Summary: ExeQution Analytics Python API
Author: ExeQution Analytics
Requires-Python: >=3.7
